deprecated_fbv/__init__.py
deprecated_fbv/create_update.py
deprecated_fbv/date_based.py
deprecated_fbv/list_detail.py
deprecated_fbv/simple.py
django_deprecated_fbv-0.1.dist-info/DESCRIPTION.rst
django_deprecated_fbv-0.1.dist-info/METADATA
django_deprecated_fbv-0.1.dist-info/metadata.json
django_deprecated_fbv-0.1.dist-info/RECORD
django_deprecated_fbv-0.1.dist-info/top_level.txt
django_deprecated_fbv-0.1.dist-info/WHEEL
