Metadata-Version: 2.0
Name: django-deprecated-fbv
Version: 0.1
Summary: Deprecated Django function based views from Django 1.4 in a neat little package.
Home-page: https://github.com/dokterbob/django-deprecated-fbv/
Author: Mathijs de Bruin
Author-email: mathijs@mathijsfietst.nl
License: BSD
Platform: UNKNOWN
Classifier: Development Status :: 3 - Alpha
Classifier: Environment :: Web Environment
Classifier: Framework :: Django
Classifier: Intended Audience :: Developers
Classifier: License :: OSI Approved :: BSD License
Classifier: Operating System :: OS Independent
Classifier: Programming Language :: Python
Classifier: Topic :: Utilities
